LICENSE
MANIFEST.in
README.md
pyproject.toml
requirements.txt
setup.py
cfunits/__init__.py
cfunits/units.py
cfunits.egg-info/PKG-INFO
cfunits.egg-info/SOURCES.txt
cfunits.egg-info/dependency_links.txt
cfunits.egg-info/requires.txt
cfunits.egg-info/top_level.txt
cfunits/etc/udunits/README
cfunits/etc/udunits/udunits2-accepted.xml
cfunits/etc/udunits/udunits2-accepted.xml.nonCF
cfunits/etc/udunits/udunits2-base.xml
cfunits/etc/udunits/udunits2-common.xml
cfunits/etc/udunits/udunits2-common.xml.nonCF
cfunits/etc/udunits/udunits2-derived.xml
cfunits/etc/udunits/udunits2-derived.xml.nonCF
cfunits/etc/udunits/udunits2-prefixes.xml
cfunits/etc/udunits/udunits2.xml
cfunits/test/__init__.py
cfunits/test/run_tests.py
cfunits/test/run_tests_and_coverage
cfunits/test/test_Units.py
cfunits/test/test_style.py