Metadata-Version: 2.1
Name: cfunits
Version: 3.3.7
Summary: A python interface to UNIDATA's UDUNITS-2 package with CF extensions 
Home-page: https://bitbucket.org/cfpython/cfunits-python
Download-URL: https://bitbucket.org/cfpython/cfunits-python/downloads
Author: David Hassell
Author-email: david.hassell@ncas.ac.uk
Maintainer: David Hassell
Maintainer-email: david.hassell@ncas.ac.uk
License: MIT
Keywords: cf,udunits,UNIDATA,netcdf,data,science,oceanography,meteorology,climate
Platform: Linux
Platform: MacOS
Platform: Windows
Classifier: Development Status :: 5 - Production/Stable
Classifier: Intended Audience :: Science/Research
Classifier: License :: OSI Approved :: MIT License
Classifier: Topic :: Scientific/Engineering
Classifier: Operating System :: OS Independent
Classifier: Programming Language :: Python :: 3
Classifier: Programming Language :: Python :: 3 :: Only
Classifier: Programming Language :: Python :: 3.6
Classifier: Programming Language :: Python :: 3.7
Classifier: Programming Language :: Python :: 3.8
Classifier: Programming Language :: Python :: 3.9
Requires-Python: >=3.6
License-File: LICENSE
Requires-Dist: cftime>=1.5.0
Requires-Dist: numpy>=1.15
Requires-Dist: packaging>=20.0
Provides-Extra: required-c-libraries
Requires-Dist: udunits2==2.2.20; extra == "required-c-libraries"
Provides-Extra: documentation
Requires-Dist: sphinx<=4,>=2; extra == "documentation"
Requires-Dist: sphinx-copybutton; extra == "documentation"
Requires-Dist: sphinx-toggleprompt; extra == "documentation"
Requires-Dist: sphinxcontrib-spelling; extra == "documentation"
Provides-Extra: pre-commit-hooks
Requires-Dist: pre-commit; extra == "pre-commit-hooks"
Requires-Dist: black; extra == "pre-commit-hooks"
Requires-Dist: docformatter; extra == "pre-commit-hooks"
Requires-Dist: flake8; extra == "pre-commit-hooks"
Requires-Dist: pydocstyle; extra == "pre-commit-hooks"
